waluigi/__init__.py
waluigi/waluigi.py
waluigi-0.1.0.dist-info/AUTHORS.rst
waluigi-0.1.0.dist-info/METADATA
waluigi-0.1.0.dist-info/WHEEL
waluigi-0.1.0.dist-info/top_level.txt
waluigi-0.1.0.dist-info/RECORD
