Metadata-Version: 2.1
Name: waluigi
Version: 0.1.0
Summary: Opinionated Luigi extensions
Home-page: https://github.com/pwoolvett/waluigi
Author: Pablo Woolvett
Author-email: pablowoolvett@gmail.com
License: UNKNOWN
Keywords: waluigi
Platform: UNKNOWN
Classifier: Development Status :: 2 - Pre-Alpha
Classifier: Intended Audience :: Developers
Classifier: Natural Language :: English
Classifier: Programming Language :: Python :: 3.6
Classifier: Programming Language :: Python :: 3.7
